{
  "project_info": {
    "project_number": "20844624231",
    "firebase_url": "https://visitnepal2020-b84e1.firebaseio.com",
    "project_id": "visitnepal2020-b84e1",
    "storage_bucket": "visitnepal2020-b84e1.appspot.com"
  },
  "client": [
    {
      "client_info": {
        "mobilesdk_app_id": "1:20844624231:android:149b6d79677c0f8d6217c2",
        "android_client_info": {
          "package_name": "com.example.visitnepal2020"
        }
      },
      "oauth_client": [
        {
          "client_id": "20844624231-q6g6fhps2ekkf80707lsa1d2pl17kdfd.apps.googleusercontent.com",
          "client_type": 3
        }
      ],
      "api_key": [
        {
          "current_key": "AIzaSyD0L6PXdZ0IJ8wmn2DnYiTELqDuSgYbRsc"
        }
      ],
      "services": {
        "appinvite_service": {
          "other_platform_oauth_client": [
            {
              "client_id": "20844624231-q6g6fhps2ekkf80707lsa1d2pl17kdfd.apps.googleusercontent.com",
              "client_type": 3
            }
          ]
        }
      }
    }
  ],
  "configuration_version": "1"
}